<COMPONENT>
	<HEADER 
		PLATEFORM="WINDOWS" 
		SERIAL="" 
		VERSION="0.101" 
		STATUS="ALPHA"
		COMPATIBILITY="ALL"
		AUTHOR="Talend" 
		RELEASE_DATE="20081030"
		STARTABLE="true" 
		EXTENSION="org.talend.designer.spss"	
		SCHEMA_AUTO_PROPAGATE="true" 
		LOG4J_ENABLED="true"
		VISIBLE="false"
	>
		<SIGNATURE></SIGNATURE>
	</HEADER>

  <FAMILIES>
    <FAMILY>Deprecated</FAMILY>
  </FAMILIES>

	<DOCUMENTATION>
		<URL />
	</DOCUMENTATION>

	<CONNECTORS>
		<CONNECTOR CTYPE="FLOW" MAX_INPUT="0" MAX_OUTPUT="1"/>
		<CONNECTOR CTYPE="ITERATE" MAX_OUTPUT="0" MAX_INPUT="1" />
		<CONNECTOR CTYPE="SUBJOB_OK" MAX_INPUT="1" />
		<CONNECTOR CTYPE="SUBJOB_ERROR" MAX_INPUT="1" />
		<CONNECTOR CTYPE="COMPONENT_OK" />
		<CONNECTOR CTYPE="COMPONENT_ERROR" />
		<CONNECTOR CTYPE="RUN_IF" />
	</CONNECTORS>

	<PARAMETERS>
		<PARAMETER NAME="MAP" FIELD="EXTERNAL" NUM_ROW="1">
			<DEFAULT />
		</PARAMETER>

		<PARAMETER NAME="SCHEMA" FIELD="SCHEMA_TYPE" REQUIRED="true" NUM_ROW="1" READONLY="true" >
		</PARAMETER>
	      
		<PARAMETER NAME="FILENAME" FIELD="FILE" NUM_ROW="10"
			REQUIRED="true" REPOSITORY_VALUE="FILE_PATH">
			<DEFAULT>"__COMP_DEFAULT_FILE_DIR__/in.sav"</DEFAULT>
		</PARAMETER>

		<PARAMETER NAME="TRANSLATELABELS" FIELD="CHECK" NUM_ROW="20"> 
			<DEFAULT>false</DEFAULT> 
		</PARAMETER>


	</PARAMETERS>

      <CODEGENERATION>
    <IMPORTS>
      <IMPORT NAME="Java_SPSS" MODULE="JSPSS.jar" MVN="mvn:org.talend.libraries/JSPSS/6.0.0"  REQUIRED="true" />
    </IMPORTS>
  </CODEGENERATION>

  <RETURNS>
      <RETURN NAME="NB_LINE" TYPE="id_Integer" AVAILABILITY="AFTER"/>
   </RETURNS>

      
</COMPONENT>
